sfmp/__init__.py
sfmp/cli.py
sfmp/feature_extractor.py
sfmp/sfmp.py
sfmp/artifacts/feature_extractor.onnx
sfmp-1.0.1.dist-info/METADATA
sfmp-1.0.1.dist-info/WHEEL
sfmp-1.0.1.dist-info/entry_points.txt
sfmp-1.0.1.dist-info/top_level.txt
sfmp-1.0.1.dist-info/RECORD
