Metadata-Version: 2.1
Name: sfmp
Version: 1.0.1
Summary: Separate images automatically
Home-page: https://github.com/psthw/sfmp
Keywords: separate,images,automatically,cluster,feature,deeplearning
Requires-Python: >=3.5, <4
Requires-Dist: pillow ==10.4.0
Requires-Dist: scikit-learn ==1.5.1
Requires-Dist: tqdm ==4.66.4
Provides-Extra: cpu
Requires-Dist: onnxruntime ==1.18.1 ; extra == 'cpu'
Provides-Extra: gpu
Requires-Dist: onnxruntime-gpu ==1.18.1 ; extra == 'gpu'
